bitsrunlogin/LoginManager.py
bitsrunlogin/__init__.py
bitsrunlogin/_decorators.py
bitsrunlogin/_encryption.py
bitsrunlogin-0.1.0.dist-info/LICENSE
bitsrunlogin-0.1.0.dist-info/METADATA
bitsrunlogin-0.1.0.dist-info/WHEEL
bitsrunlogin-0.1.0.dist-info/top_level.txt
bitsrunlogin-0.1.0.dist-info/RECORD
